agentDVerse/__init__.py
agentDVerse/agent.py
database_manager/__init__.py
database_manager/database_manager.py
kafka_manager/__init__.py
kafka_manager/kafka_manager.py
status_manager/__init__.py
status_manager/status_manager.py
dverse_agent_python-1.0.5.dist-info/METADATA
dverse_agent_python-1.0.5.dist-info/WHEEL
dverse_agent_python-1.0.5.dist-info/top_level.txt
dverse_agent_python-1.0.5.dist-info/RECORD
