Metadata-Version: 2.1
Name: dverse_agent_python
Version: 1.0.5
Summary: A package for creating an Agent for the DVerse platform.
Home-page: https://pypi.org/project/dverse-agent-python/
Author: Fontys-Dverse
Requires-Dist: argon2-cffi ==23.1.0
Requires-Dist: argon2-cffi-bindings ==21.2.0
Requires-Dist: azure-core ==1.30.1
Requires-Dist: azure-storage-blob ==12.20.0
Requires-Dist: boolean.py ==4.0
Requires-Dist: CacheControl ==0.14.0
Requires-Dist: certifi ==2024.6.2
Requires-Dist: cffi ==1.16.0
Requires-Dist: cfgv ==3.4.0
Requires-Dist: charset-normalizer ==3.3.2
Requires-Dist: click ==8.1.7
Requires-Dist: colorama ==0.4.6
Requires-Dist: confluent-kafka ==2.4.0
Requires-Dist: cryptography ==42.0.8
Requires-Dist: cyclonedx-python-lib ==7.4.0
Requires-Dist: defusedxml ==0.7.1
Requires-Dist: distlib ==0.3.8
Requires-Dist: environs ==9.5.0
Requires-Dist: filelock ==3.14.0
Requires-Dist: fsspec ==2024.6.0
Requires-Dist: grpcio ==1.60.0
Requires-Dist: html5lib ==1.1
Requires-Dist: huggingface-hub ==0.23.2
Requires-Dist: identify ==2.5.36
Requires-Dist: idna ==3.7
Requires-Dist: isodate ==0.6.1
Requires-Dist: Jinja2 ==3.1.4
Requires-Dist: joblib ==1.4.2
Requires-Dist: license-expression ==30.3.0
Requires-Dist: markdown-it-py ==3.0.0
Requires-Dist: MarkupSafe ==2.1.5
Requires-Dist: marshmallow ==3.21.2
Requires-Dist: mdurl ==0.1.2
Requires-Dist: minio ==7.2.7
Requires-Dist: mpmath ==1.3.0
Requires-Dist: msgpack ==1.0.8
Requires-Dist: networkx ==3.3
Requires-Dist: nodeenv ==1.9.1
Requires-Dist: numpy ==1.26.4
Requires-Dist: packageurl-python ==0.15.0
Requires-Dist: packaging ==24.0
Requires-Dist: pandas ==2.2.2
Requires-Dist: pillow ==10.3.0
Requires-Dist: pip-api ==0.0.33
Requires-Dist: pip-requirements-parser ==32.0.1
Requires-Dist: pip-audit ==2.7.3
Requires-Dist: platformdirs ==4.2.2
Requires-Dist: pre-commit ==3.7.1
Requires-Dist: proto-plus ==1.23.0
Requires-Dist: protobuf ==4.25.3
Requires-Dist: py-serializable ==1.0.3
Requires-Dist: pyarrow ==16.1.0
Requires-Dist: pyasn1 ==0.6.0
Requires-Dist: pyasn1-modules ==0.4.0
Requires-Dist: pycparser ==2.22
Requires-Dist: pycryptodome ==3.20.0
Requires-Dist: Pygments ==2.18.0
Requires-Dist: pymilvus ==2.4.1
Requires-Dist: pyparsing ==3.1.2
Requires-Dist: python-dateutil ==2.9.0.post0
Requires-Dist: python-dotenv ==1.0.1
Requires-Dist: python-slugify ==8.0.4
Requires-Dist: pytz ==2024.1
Requires-Dist: PyYAML ==6.0.1
Requires-Dist: regex ==2024.5.15
Requires-Dist: requests ==2.32.3
Requires-Dist: rich ==13.7.1
Requires-Dist: safetensors ==0.4.3
Requires-Dist: scikit-learn ==1.5.0
Requires-Dist: scipy ==1.13.1
Requires-Dist: sentence-transformers ==3.0.0
Requires-Dist: setuptools ==70.0.0
Requires-Dist: six ==1.16.0
Requires-Dist: sortedcontainers ==2.4.0
Requires-Dist: sympy ==1.12.1
Requires-Dist: text-unidecode ==1.3
Requires-Dist: threadpoolctl ==3.5.0
Requires-Dist: tokenizers ==0.19.1
Requires-Dist: toml ==0.10.2
Requires-Dist: torch ==2.3.0
Requires-Dist: tqdm ==4.66.4
Requires-Dist: transformers ==4.41.2
Requires-Dist: typing-extensions ==4.12.1
Requires-Dist: tzdata ==2024.1
Requires-Dist: ujson ==5.10.0
Requires-Dist: urllib3 ==2.2.2
Requires-Dist: virtualenv ==20.26.2
Requires-Dist: webencodings ==0.5.1
Requires-Dist: wheel ==0.43.0
